{"kind":"identitytoolkit#DownloadAccountResponse","users":[{"localId":"hR7ygJIXq2ttOoEloJC7tn9hOMUF","displayName":"Orange Raccoon","screenName":"raccoon_orange","email":"orange.raccoon.357@example.com","emailVerified":true,"lastLoginAt":"1675822727095","providerUserInfo":[{"providerId":"google.com","rawId":"6040404496286369953926434896722854227473","federatedId":"6040404496286369953926434896722854227473","displayName":"Orange Raccoon","email":"orange.raccoon.357@example.com","screenName":"raccoon_orange"}],"lastRefreshAt":"2023-02-08T02:18:47.095Z"}]}